<?xml version="1.1" encoding="UTF-8" standalone="no"?>
<databaseChangeLog xmlns="http://www.liquibase.org/xml/ns/dbchangelog"
                   xmlns:ext="http://www.liquibase.org/xml/ns/dbchangelog-ext"
                   xmlns:xsi="http://www.w3.org/2001/XMLSchema-instance"
                   xsi:schemaLocation="http://www.liquibase.org/xml/ns/dbchangelog-ext
    http://www.liquibase.org/xml/ns/dbchangelog/dbchangelog-ext.xsd
    http://www.liquibase.org/xml/ns/dbchangelog
    http://www.liquibase.org/xml/ns/dbchangelog/dbchangelog-4.13.xsd">

    <changeSet id="1" author="futakotome">
        <sql dbms="postgresql" endDelimiter=";">
            create schema admin
        </sql>
        <sql dbms="postgresql" endDelimiter=";">
            create schema user1
        </sql>
    </changeSet>
    <changeSet id="1.1" author="futakotome">
        <sqlFile path="./schema/V1.0.0__create_fruits.sql"/>
    </changeSet>
</databaseChangeLog>